pyproxystore/__init__.py
pyproxystore/_async.py
pyproxystore-1.0.3.dist-info/LICENSE
pyproxystore-1.0.3.dist-info/METADATA
pyproxystore-1.0.3.dist-info/WHEEL
pyproxystore-1.0.3.dist-info/top_level.txt
pyproxystore-1.0.3.dist-info/RECORD
