Metadata-Version: 2.2
Name: pyproxystore
Version: 1.0.3
Summary: pyproxystore - Unofficial python library for working with proxy-store.com
Home-page: https://github.com/makarworld/pyproxystore.git
Download-URL: https://github.com/makarworld/pyproxystore/archive/refs/tags/v1.0.3.zip
Author: abuztrade
Author-email: abuztrade.work@gmail.com
License: MIT License
Classifier: Development Status :: 4 - Beta
Classifier: Topic :: Communications :: Email
Classifier: Operating System :: OS Independent
Classifier: License :: OSI Approved :: MIT License
Classifier: Programming Language :: Python :: 3.10
Classifier: Intended Audience :: Developers
Classifier: Intended Audience :: Customer Service
Classifier: Intended Audience :: Financial and Insurance Industry
Requires-Python: >=3.10.0
License-File: LICENSE
Requires-Dist: requests
Dynamic: author
Dynamic: author-email
Dynamic: classifier
Dynamic: description
Dynamic: description-content-type
Dynamic: download-url
Dynamic: home-page
Dynamic: license
Dynamic: requires-dist
Dynamic: requires-python
Dynamic: summary
